{"users":[{"userId":"239845f4-4e3d-4cfb-8525-5ca6805f1d6c","username":"Kenna_Lueilwitz","email":"Fidel16@gmail.com","avatar":"https://cloudflare-ipfs.com/ipfs/Qmd3W5DuhgHirLHGVixi6V76LhCkZUz6pnFt5AJBiyvHye/avatar/16.jpg","password":"38p2W27b0m2E4Vv","birthdate":"1968-05-29T06:28:52.179Z","registeredAt":"2022-11-03T09:03:59.173Z"},{"userId":"8ef1b5eb-1951-4d13-bab1-0c81ec733081","username":"Jane_Schultz","email":"Vernon41@gmail.com","avatar":"https://cloudflare-ipfs.com/ipfs/Qmd3W5DuhgHirLHGVixi6V76LhCkZUz6pnFt5AJBiyvHye/avatar/1022.jpg","password":"llY1eqGh3_7t7Gq","birthdate":"1983-01-01T12:09:25.578Z","registeredAt":"2022-01-06T08:31:13.171Z"},{"userId":"cc101058-dc7a-4dbe-99cd-f9de27bb4ebb","username":"Jermain_Bogisich","email":"Herman53@yahoo.com","avatar":"https://cloudflare-ipfs.com/ipfs/Qmd3W5DuhgHirLHGVixi6V76LhCkZUz6pnFt5AJBiyvHye/avatar/68.jpg","password":"ILHNEGqNNtyiANA","birthdate":"1946-04-07T23:05:02.859Z","registeredAt":"2022-02-24T01:43:56.228Z"},{"userId":"7d6b5855-4427-43c9-a338-1eb73921e4e2","username":"Adah_Kling96","email":"Gregory.Mann@yahoo.com","avatar":"https://cloudflare-ipfs.com/ipfs/Qmd3W5DuhgHirLHGVixi6V76LhCkZUz6pnFt5AJBiyvHye/avatar/314.jpg","password":"UejuXX9nP5jJ1Oh","birthdate":"1956-05-06T12:47:09.790Z","registeredAt":"2022-01-10T18:19:45.953Z"},{"userId":"7fde7cff-9e24-4735-a015-a6aed55da25d","username":"Alice24","email":"Kathleen_Johnston55@gmail.com","avatar":"https://cloudflare-ipfs.com/ipfs/Qmd3W5DuhgHirLHGVixi6V76LhCkZUz6pnFt5AJBiyvHye/avatar/683.jpg","password":"TzR8ty6a6p2zq8C","birthdate":"2003-01-24T04:40:26.100Z","registeredAt":"2022-06-13T08:11:03.167Z"},{"userId":"274b77fb-46e8-493d-8017-7c0297d8be95","username":"Loma57","email":"Bell_Padberg@gmail.com","avatar":"https://cloudflare-ipfs.com/ipfs/Qmd3W5DuhgHirLHGVixi6V76LhCkZUz6pnFt5AJBiyvHye/avatar/234.jpg","password":"d1QE4YiIrx3gRJ5","birthdate":"1953-10-05T09:31:07.236Z","registeredAt":"2021-11-12T19:28:36.404Z"},{"userId":"3ba78d17-db0f-4312-b1c8-74be3f44f6ba","username":"Robb77","email":"Della.Keebler@yahoo.com","avatar":"https://cloudflare-ipfs.com/ipfs/Qmd3W5DuhgHirLHGVixi6V76LhCkZUz6pnFt5AJBiyvHye/avatar/656.jpg","password":"gOqC7OPGAtC_YWQ","birthdate":"1982-03-07T07:41:02.684Z","registeredAt":"2022-02-06T05:09:06.971Z"},{"userId":"5d0e3a9a-a966-45be-8ade-fbb5742adb7b","username":"Marty.Douglas","email":"Ebony.Powlowski@yahoo.com","avatar":"https://cloudflare-ipfs.com/ipfs/Qmd3W5DuhgHirLHGVixi6V76LhCkZUz6pnFt5AJBiyvHye/avatar/356.jpg","password":"0ZHM5OKouzcKKQ4","birthdate":"1981-04-19T20:21:37.420Z","registeredAt":"2022-09-04T21:46:00.528Z"},{"userId":"ca9460f7-aae6-4b98-8e4a-0c4d371496a4","username":"Conrad_Franecki","email":"Lenore_Purdy@hotmail.com","avatar":"https://cloudflare-ipfs.com/ipfs/Qmd3W5DuhgHirLHGVixi6V76LhCkZUz6pnFt5AJBiyvHye/avatar/367.jpg","password":"uQ6MNiW4uNcW2_j","birthdate":"1962-07-28T11:30:55.927Z","registeredAt":"2022-03-29T11:24:27.450Z"},{"userId":"178ec3e9-bdb4-498c-910f-6ce0bd88ddc5","username":"Jaylen_Schuppe","email":"Carleton_Mann60@hotmail.com","avatar":"https://cloudflare-ipfs.com/ipfs/Qmd3W5DuhgHirLHGVixi6V76LhCkZUz6pnFt5AJBiyvHye/avatar/908.jpg","password":"s7cAgEJb9pOVMRd","birthdate":"1976-04-08T04:34:41.606Z","registeredAt":"2021-12-20T14:08:48.718Z"}],"books":[{"id":"7ab53639-a56b-4207-8cf6-e544d5f13d06","title":"denude settler","description":"install dilution. There is restroom","pages":343},{"id":"77002297-f5d3-45b0-81f0-643cd6d4c138","title":"tyrannize solitaire","description":"trick offer. There is mainstream","pages":915},{"id":"9dba0558-9d04-403f-8218-bab0fbf12ee2","title":"toddle pathology","description":"crucify monster. There is inspector","pages":693},{"id":"d05c2721-de21-4eea-8c17-681639c1e7c2","title":"ferry babushka","description":"debilitate omelet. There is speakerphone","pages":780},{"id":"f225da13-85e8-4a27-bb11-a3533d57edb2","title":"unfurl shadowbox","description":"disguise catalyst. There is coverall","pages":533},{"id":"09603e3b-7647-4c60-aae8-39172341b7c7","title":"languish center","description":"subject cleric. There is sampan","pages":84},{"id":"7cd9642d-328c-4500-a868-5a03ead8f86c","title":"pardon nexus","description":"except visor. There is hippopotamus","pages":588},{"id":"d1ad2736-2d70-4c30-8627-4795f528014e","title":"blabber mangle","description":"egg leaf. There is cornflakes","pages":263},{"id":"881c1767-d4f8-486c-90da-56eeb12511c5","title":"dump decadence","description":"exploit bestseller. There is servant","pages":141},{"id":"d34d80c7-f88b-41a8-a344-7dc43aee7206","title":"count bellows","description":"embalm cross. There is swath","pages":722},{"id":"470a0cd6-6f43-43ce-ab2e-94f3cb095c01","title":"slide mixture","description":"resemble midnight. There is abuse","pages":290},{"id":"137f7e50-2e73-4a50-8c2b-8ad14e56f4b6","title":"rehouse following","description":"accost leveret. There is timbale","pages":95},{"id":"39ea93e8-8dce-4221-8d11-ea716a9a0e3b","title":"mortify millstone","description":"scale gerbil. There is cold","pages":794},{"id":"3e329657-50e6-4db4-b801-88697e503c3b","title":"swat soundness","description":"strew jot. There is notoriety","pages":835},{"id":"410ed59b-1af7-413c-9ec4-6a84363d39f6","title":"preselect loan","description":"defy anchovy. There is elixir","pages":797},{"id":"40cfa3ff-13f3-4198-b7fd-d2a27258211d","title":"extinguish laboratory","description":"aerate perch. There is digestive","pages":77},{"id":"4cdd1f1a-2c8d-49f7-bb04-f3b89415067d","title":"slaughter capacity","description":"message fleece. There is unblinking","pages":738},{"id":"2cfd6ca6-10f9-4575-9b78-0fed0e1feef7","title":"irradiate chipmunk","description":"price timpani. There is police","pages":143},{"id":"118ffd16-07e1-4ab7-8311-36cbc1e7cd6d","title":"romanticise wave","description":"sidestep eyestrain. There is progenitor","pages":436},{"id":"f4e85735-74cf-415e-bf9f-868f58991a13","title":"idle temp","description":"glut bulk. There is guarantee","pages":519}]}